aws_cdk/assets_docker/_jsii/__init__.py
aws_cdk/assets_docker/_jsii/assets-docker@0.35.0.jsii.tgz
aws_cdk.assets_docker-0.35.0.dist-info/METADATA
aws_cdk.assets_docker-0.35.0.dist-info/WHEEL
aws_cdk.assets_docker-0.35.0.dist-info/top_level.txt
aws_cdk.assets_docker-0.35.0.dist-info/RECORD
